MANIFEST.in
README.md
licence.txt
setup.cfg
setup.py
weibopy/__init__.py
weibopy/auth.py
weibopy/exceptions.py
weibopy/weibo.py
weibopy.egg-info/PKG-INFO
weibopy.egg-info/SOURCES.txt
weibopy.egg-info/dependency_links.txt
weibopy.egg-info/not-zip-safe
weibopy.egg-info/requires.txt
weibopy.egg-info/top_level.txt