Metadata-Version: 2.1
Name: weibopy
Version: 0.1.2
Summary: Sina Weibo API SDK
Home-page: https://github.com/nooperpudd/weibopy
Author: Winton Wang
Author-email: 365504029@qq.com
License: BSD
Platform: UNKNOWN
Classifier: Development Status :: 5 - Production/Stable
Classifier: Intended Audience :: Developers
Classifier: License :: OSI Approved :: BSD License
Classifier: Programming Language :: Python
Classifier: Programming Language :: Python :: 3
Classifier: Programming Language :: Python :: 3.4
Classifier: Programming Language :: Python :: 3.5
Classifier: Programming Language :: Python :: 3.6
Classifier: Environment :: Web Environment
